confluence_to_sqlite/__init__.py
confluence_to_sqlite/cli.py
confluence_to_sqlite-0.0.0.dist-info/LICENSE
confluence_to_sqlite-0.0.0.dist-info/METADATA
confluence_to_sqlite-0.0.0.dist-info/WHEEL
confluence_to_sqlite-0.0.0.dist-info/entry_points.txt
confluence_to_sqlite-0.0.0.dist-info/top_level.txt
confluence_to_sqlite-0.0.0.dist-info/RECORD
