Metadata-Version: 2.1
Name: confluence-to-sqlite
Version: 0.0.0
Summary: CLI tool for loading data from a Confluence instance into a SQLite database
Home-page: https://github.com/ryancheley/confluence-to-sqlite
Author: Ryan Cheley
License: Apache License, Version 2.0
Project-URL: Issues, https://github.com/ryancheley/confluence-to-sqlite/issues
Project-URL: CI, https://github.com/ryancheley/confluence-to-sqlite/actions
Project-URL: Changelog, https://github.com/ryancheley/confluence-to-sqlite/releases
Platform: UNKNOWN
Requires-Python: >=3.6
Requires-Dist: sqlite-utils
Requires-Dist: click
Provides-Extra: test
Requires-Dist: pytest ; extra == 'test'
